Metadata-Version: 1.1
Name: cskv
Version: 1.0.0.dev8
Summary: Config parser for INI and RAW formatted files
Home-page: https://github.com/julenl/cskv
Author: Julen Larrucea
Author-email: julen@larrucea.eu
License: GNU General Public License v2 (GPLv2)
Download-URL: https://github.com/julenl/cskv/archive/0.1.tar.gz
Keywords: config,ini,raw,parser,non-interactive
Platform: UNKNOWN
Classifier: Operating System :: POSIX
Classifier: Programming Language :: Python
Classifier: Programming Language :: Python :: 2
Classifier: Topic :: System :: Systems Administration
